./.gitignore
./PKG-INFO
./__init__.py
./image_vec_rep_resnet.py
./pyproject.toml
image_vec_rep_resnet-0.9.0.dist-info/METADATA
image_vec_rep_resnet-0.9.0.dist-info/WHEEL
image_vec_rep_resnet-0.9.0.dist-info/RECORD
